chat_ideyalabs/__init__.py
chat_ideyalabs/config.py
chat_ideyalabs/api/__init__.py
chat_ideyalabs/api/auth.py
chat_ideyalabs/api/main.py
chat_ideyalabs/api/models.py
chat_ideyalabs/core/__init__.py
chat_ideyalabs/core/base.py
chat_ideyalabs/core/chat_ideyalabs.py
chat_ideyalabs/utils/__init__.py
chat_ideyalabs/utils/api_client.py
chat_ideyalabs/utils/api_key_manager.py
chat_ideyalabs/utils/log_sanitizer.py
chat_ideyalabs/utils/mongodb_logger.py
chat_ideyalabs-0.1.5.dist-info/METADATA
chat_ideyalabs-0.1.5.dist-info/WHEEL
chat_ideyalabs-0.1.5.dist-info/entry_points.txt
chat_ideyalabs-0.1.5.dist-info/top_level.txt
chat_ideyalabs-0.1.5.dist-info/RECORD
