Metadata-Version: 2.4
Name: chat-ideyalabs
Version: 0.1.5
Summary: Secure LLM API wrapper with user authentication and request validation
Home-page: https://github.com/ideyalabs/chat-ideyalabs
Author: Ideyalabs
Author-email: support@ideyalabs.com
Project-URL: Bug Tracker, https://github.com/ideyalabs/chat-ideyalabs/issues
Project-URL: Documentation, https://github.com/ideyalabs/chat-ideyalabs/blob/main/PYPI_PUBLISHING_GUIDE.md
Keywords: llm,chatbot,api,authentication,security,openai,langchain,artificial-intelligence,machine-learning
Classifier: Development Status :: 4 - Beta
Classifier: Intended Audience :: Developers
Classifier: License :: OSI Approved :: MIT License
Classifier: Operating System :: OS Independent
Classifier: Programming Language :: Python :: 3
Classifier: Programming Language :: Python :: 3.8
Classifier: Programming Language :: Python :: 3.9
Classifier: Programming Language :: Python :: 3.10
Classifier: Programming Language :: Python :: 3.11
Classifier: Topic :: Software Development :: Libraries :: Python Modules
Classifier: Topic :: Internet :: WWW/HTTP :: HTTP Servers
Classifier: Topic :: Scientific/Engineering :: Artificial Intelligence
Requires-Python: >=3.8
Requires-Dist: httpx>=0.24.0
Requires-Dist: pydantic>=2.0.0
Requires-Dist: fastapi>=0.100.0
Requires-Dist: uvicorn>=0.20.0
Requires-Dist: motor>=3.0.0
Requires-Dist: pymongo>=4.0.0
Requires-Dist: pytest>=7.0.0
Requires-Dist: pytest-asyncio>=0.20.0
Requires-Dist: black>=23.0.0
Requires-Dist: isort>=5.12.0
Requires-Dist: mypy>=1.0.0
Requires-Dist: python-dotenv>=1.0.0
Provides-Extra: dev
Requires-Dist: pytest>=6.0; extra == "dev"
Requires-Dist: pytest-asyncio>=0.18.0; extra == "dev"
Requires-Dist: black>=22.0.0; extra == "dev"
Requires-Dist: isort>=5.0.0; extra == "dev"
Requires-Dist: flake8>=4.0.0; extra == "dev"
Requires-Dist: mypy>=0.950; extra == "dev"
Provides-Extra: build
Requires-Dist: build>=0.10.0; extra == "build"
Requires-Dist: twine>=4.0.0; extra == "build"
Dynamic: author
Dynamic: author-email
Dynamic: classifier
Dynamic: description
Dynamic: description-content-type
Dynamic: home-page
Dynamic: keywords
Dynamic: project-url
Dynamic: provides-extra
Dynamic: requires-dist
Dynamic: requires-python
Dynamic: summary
